<?xml version="1.0" encoding="UTF-8"?>
<BodyUpload>
	<SystemInformation>
		<ExportDateTime>
			<year>2015</year>
			<month>04</month>
			<day>08</day>
			<hours>13</hours>
			<minutes>12</minutes>
			<seconds>59</seconds>
		</ExportDateTime>
		<FullExport>1</FullExport>
		<user>Гриненко Михаил (дизайнер)</user>
	</SystemInformation>
	<PricesTypes>
		<type>
			<id>288427e0-9732-11db-bbb4-0017315894a1</id>
			<typeName>Розничная</typeName>
			<default>1</default>
		</type>
		<type>
			<id>feff0694-99ab-11db-937f-000e0c431b59</id>
			<typeName>Оптовая</typeName>
			<default>0</default>
		</type>
		<type>
			<id>86157e21-e56b-11dc-8b6b-000e0c431b58</id>
			<typeName>Спец. цена</typeName>
			<default>0</default>
		</type>
	</PricesTypes>
	<Properties>
		<property>
			<id>d624040a-3bb6-11e3-80e1-005056be1f7a</id>
			<propertyName>Основа</propertyName>
			<filterType>groupSelect</filterType>
			<valueType>varchar</valueType>
			<oneOfAllValues>0</oneOfAllValues>
		</property>
		<property>
			<id>0a552a3f-3bb7-11e3-80e1-005056be1f7a</id>
			<propertyName>Цвет</propertyName>
			<filterType>groupSelect</filterType>
			<valueType>varchar</valueType>
			<oneOfAllValues>0</oneOfAllValues>
		</property>
		<property>
			<id>c17ab514-3bbc-11e3-80e1-005056be1f7a</id>
			<propertyName>Блеск</propertyName>
			<filterType>groupSelect</filterType>
			<valueType>varchar</valueType>
			<oneOfAllValues>0</oneOfAllValues>
		</property>
		<property>
			<id>27c97b3a-3bc1-11e3-80e1-005056be1f7a</id>
			<propertyName>Область применения</propertyName>
			<filterType>groupSelect</filterType>
			<valueType>varchar</valueType>
			<oneOfAllValues>0</oneOfAllValues>
		</property>
		<property>
			<id>618eeb90-3bc1-11e3-80e1-005056be1f7a</id>
			<propertyName>Особенности</propertyName>
			<filterType>groupSelect</filterType>
			<valueType>varchar</valueType>
			<oneOfAllValues>0</oneOfAllValues>
		</property>
		<property>
			<id>0569475c-1474-11e3-82b9-0050569a1080</id>
			<propertyName>Тип</propertyName>
			<filterType>groupSelect</filterType>
			<valueType>varchar</valueType>
			<oneOfAllValues>0</oneOfAllValues>
		</property>
		<property>
			<id>0beb7c10-76ad-11e3-8868-005056be1f7a</id>
			<propertyName>Износоустойчивость</propertyName>
			<filterType>groupSelect</filterType>
			<valueType>varchar</valueType>
			<oneOfAllValues>0</oneOfAllValues>
		</property>
		<property>
			<id>6cd386f1-3a4b-11e3-88c8-005056be1f7a</id>
			<propertyName>Объем (л)</propertyName>
			<filterType>intRange</filterType>
			<valueType>float</valueType>
			<oneOfAllValues>0</oneOfAllValues>
		</property>
		<property>
			<id>bbea9c1a-3a4b-11e3-88c8-005056be1f7a</id>
			<propertyName>Назначение</propertyName>
			<filterType>groupSelect</filterType>
			<valueType>varchar</valueType>
			<oneOfAllValues>0</oneOfAllValues>
		</property>
		<property>
			<id>cce0ab91-6a67-11e4-8945-005056be1f7a</id>
			<propertyName>Страна-производитель</propertyName>
			<filterType>groupSelect</filterType>
			<valueType>varchar</valueType>
			<oneOfAllValues>0</oneOfAllValues>
		</property>
		<property>
			<id>e765ba72-107d-11e3-8a5d-0050569a1080</id>
			<propertyName>База</propertyName>
			<filterType>groupSelect</filterType>
			<valueType>varchar</valueType>
			<oneOfAllValues>0</oneOfAllValues>
		</property>
		<property>
			<id>e765ba75-107d-11e3-8a5d-0050569a1080</id>
			<propertyName>Вес (кг)</propertyName>
			<filterType>intRange</filterType>
			<valueType>float</valueType>
			<oneOfAllValues>0</oneOfAllValues>
		</property>
		<property>
			<id>a34e94dc-9f77-11e3-9686-005056be1f7c</id>
			<propertyName>Морозостойкость</propertyName>
			<filterType>groupSelect</filterType>
			<valueType>varchar</valueType>
			<oneOfAllValues>0</oneOfAllValues>
		</property>
		<property>
			<id>6e62ed56-970e-11e4-9be0-005056be1f7c</id>
			<propertyName>Упаковка</propertyName>
			<filterType>groupSelect</filterType>
			<valueType>varchar</valueType>
			<oneOfAllValues>0</oneOfAllValues>
		</property>
		<property>
			<id>c2267174-970e-11e4-9be0-005056be1f7c</id>
			<propertyName>Длина (м)</propertyName>
			<filterType>intRange</filterType>
			<valueType>float</valueType>
			<oneOfAllValues>0</oneOfAllValues>
		</property>
		<property>
			<id>42d0b52f-970f-11e4-9be0-005056be1f7c</id>
			<propertyName>Вид</propertyName>
			<filterType>groupSelect</filterType>
			<valueType>varchar</valueType>
			<oneOfAllValues>0</oneOfAllValues>
		</property>
		<property>
			<id>0e31c585-9718-11e4-9be0-005056be1f7c</id>
			<propertyName>Ширина (м)</propertyName>
			<filterType>intRange</filterType>
			<valueType>float</valueType>
			<oneOfAllValues>0</oneOfAllValues>
		</property>
		<property>
			<id>1452d640-9718-11e4-9be0-005056be1f7c</id>
			<propertyName>Толщина (м)</propertyName>
			<filterType>intRange</filterType>
			<valueType>float</valueType>
			<oneOfAllValues>0</oneOfAllValues>
		</property>
		<property>
			<id>24cace4a-9718-11e4-9be0-005056be1f7c</id>
			<propertyName>Высота (м)</propertyName>
			<filterType>intRange</filterType>
			<valueType>float</valueType>
			<oneOfAllValues>0</oneOfAllValues>
		</property>
		<property>
			<id>1ea6fcc4-d206-11e4-9be0-005056be1f7c</id>
			<propertyName>Размер зерна (мм)</propertyName>
			<filterType>intRange</filterType>
			<valueType>int</valueType>
			<oneOfAllValues>0</oneOfAllValues>
		</property>
		<property>
			<id>d17cb785-d20b-11e4-9be0-005056be1f7c</id>
			<propertyName>Объем (мл)</propertyName>
			<filterType>intRange</filterType>
			<valueType>int</valueType>
			<oneOfAllValues>0</oneOfAllValues>
		</property>
		<property>
			<id>1d08380b-ce34-11e4-a80e-005056be1f7a</id>
			<propertyName>Вес (гр)</propertyName>
			<filterType>intRange</filterType>
			<valueType>int</valueType>
			<oneOfAllValues>0</oneOfAllValues>
		</property>
		<property>
			<id>e8287600-ad96-11e3-b114-005056be1f7c</id>
			<propertyName>Брэнд</propertyName>
			<filterType>groupSelect</filterType>
			<valueType>varchar</valueType>
			<oneOfAllValues>0</oneOfAllValues>
		</property>
		<property>
			<id>e2e87ce8-ad99-11e3-b114-005056be1f7c</id>
			<propertyName>Расход</propertyName>
			<filterType>intRange</filterType>
			<valueType>float</valueType>
			<oneOfAllValues>0</oneOfAllValues>
		</property>
		<property>
			<id>5ca72995-ad9a-11e3-b114-005056be1f7c</id>
			<propertyName>Диаметр (м)</propertyName>
			<filterType>intRange</filterType>
			<valueType>float</valueType>
			<oneOfAllValues>0</oneOfAllValues>
		</property>
	</Properties>
	<Groups>
		<Group>
			<id>445b4527-ddb0-11e4-8114-00155d3703b3</id>
			<groupName>ГКЛ</groupName>
			<shown>1</shown>
			<showInHierarchy>1</showInHierarchy>
		</Group>
		<Group>
			<id>5285c686-ddb0-11e4-8114-00155d3703b3</id>
			<groupName>Гипсокартон</groupName>
			<shown>1</shown>
			<showInHierarchy>1</showInHierarchy>
		</Group>
		<Group>
			<id>c230c98c-ddb0-11e4-8114-00155d3703b3</id>
			<groupName>DANOGIPS</groupName>
			<shown>1</shown>
			<showInHierarchy>1</showInHierarchy>
		</Group>
		<Group>
			<id>0ff76d38-da05-11e4-8111-00155d3703b3</id>
			<groupName>Лакокрасочная продукция</groupName>
			<shown>1</shown>
			<showInHierarchy>1</showInHierarchy>
		</Group>
		<Group>
			<id>a9a85653-da05-11e4-8111-00155d3703b3</id>
			<groupName>Акриловая краска</groupName>
			<shown>1</shown>
			<showInHierarchy>1</showInHierarchy>
		</Group>
		<Group>
			<id>ab721020-ddae-11e4-8114-00155d3703b3</id>
			<groupName>DALI</groupName>
			<shown>1</shown>
			<showInHierarchy>1</showInHierarchy>
		</Group>
	</Groups>
	<GroupsHierarchy>
		<Relation>
			<group>5285c686-ddb0-11e4-8114-00155d3703b3</group>
			<parentGroup>445b4527-ddb0-11e4-8114-00155d3703b3</parentGroup>
		</Relation>
		<Relation>
			<group>c230c98c-ddb0-11e4-8114-00155d3703b3</group>
			<parentGroup>5285c686-ddb0-11e4-8114-00155d3703b3</parentGroup>
		</Relation>
		<Relation>
			<group>a9a85653-da05-11e4-8111-00155d3703b3</group>
			<parentGroup>0ff76d38-da05-11e4-8111-00155d3703b3</parentGroup>
		</Relation>
		<Relation>
			<group>ab721020-ddae-11e4-8114-00155d3703b3</group>
			<parentGroup>a9a85653-da05-11e4-8111-00155d3703b3</parentGroup>
		</Relation>
	</GroupsHierarchy>
	<PropertiesInGroups/>
	<Items>
		<Item>
			<id>83afb766-99a5-11db-937f-000e0c431b59</id>
			<itemName>ГВЛВ 2500х1200 х 10.0 мм Кнауф  (50шт/уп)</itemName>
			<group>445b4527-ddb0-11e4-8114-00155d3703b3</group>
			<amount>686</amount>
			<minAmount>380</minAmount>
			<description>0</description>
			<shown>1</shown>
			<action>0</action>
			<prices>
				<price>
					<id>86157e21-e56b-11dc-8b6b-000e0c431b58</id>
					<value>409</value>
				</price>
				<price>
					<id>feff0694-99ab-11db-937f-000e0c431b59</id>
					<value>420</value>
				</price>
				<price>
					<id>288427e0-9732-11db-bbb4-0017315894a1</id>
					<value>453</value>
				</price>
			</prices>
			<propertiesValues>
				<propertyValue>
					<property>e8287600-ad96-11e3-b114-005056be1f7c</property>
					<value>DANOGIPS</value>
					<measure/>
				</propertyValue>
				<propertyValue>
					<property>cce0ab91-6a67-11e4-8945-005056be1f7a</property>
					<value>Россия</value>
					<measure/>
				</propertyValue>
				<propertyValue>
					<property>42d0b52f-970f-11e4-9be0-005056be1f7c</property>
					<value>гипсокартон</value>
					<measure/>
				</propertyValue>
			</propertiesValues>
		</Item>
		<Item>
			<id>1ae96ec3-10cc-11e4-8071-005056be1f7b</id>
			<itemName>ГКЛ 2500х1200х12,5мм  Danogips (62шт/уп)</itemName>
			<group>c230c98c-ddb0-11e4-8114-00155d3703b3</group>
			<amount>7520</amount>
			<minAmount>30</minAmount>
			<description>Плита гипсовая обычная с утонённой кромкой применяется внутри помещений с нормальной влажностью. Используется для создания ненесущих перегородок, изготовления декоративных и звукопоглащающих изделий.</description>
			<shown>1</shown>
			<action>0</action>
			<prices>
				<price>
					<id>86157e21-e56b-11dc-8b6b-000e0c431b58</id>
					<value>165</value>
				</price>
				<price>
					<id>feff0694-99ab-11db-937f-000e0c431b59</id>
					<value>167</value>
				</price>
				<price>
					<id>288427e0-9732-11db-bbb4-0017315894a1</id>
					<value>175</value>
				</price>
			</prices>
			<propertiesValues>
				<propertyValue>
					<property>e8287600-ad96-11e3-b114-005056be1f7c</property>
					<value>DANOGIPS</value>
					<measure/>
				</propertyValue>
				<propertyValue>
					<property>cce0ab91-6a67-11e4-8945-005056be1f7a</property>
					<value>Россия</value>
					<measure/>
				</propertyValue>
				<propertyValue>
					<property>42d0b52f-970f-11e4-9be0-005056be1f7c</property>
					<value>гипсокартон</value>
					<measure/>
				</propertyValue>
			</propertiesValues>
		</Item>
		<Item>
			<id>4c562149-49b3-11e2-96a1-005056be271d</id>
			<itemName>ПГП полнотелая 667*500*80мм (30шт/уп)</itemName>
			<group>5285c686-ddb0-11e4-8114-00155d3703b3</group>
			<amount>838</amount>
			<minAmount>0</minAmount>
			<description>Пазогребневые плиты из гипсового вяжущего с добавлением пластифицирующих и гидрофобных добавок предназначены для устройства перегородок в зданиях и помещениях различного назначения. Изготовлены из экологически чистого природного материала, являются негорючими, не содержат токсических веществ, не имеют запаха, обладают высокой звукоизолирующей способностью и высокой паро-, газопроницаемостью.</description>
			<shown>1</shown>
			<action>0</action>
			<prices>
				<price>
					<id>86157e21-e56b-11dc-8b6b-000e0c431b58</id>
					<value>185</value>
				</price>
				<price>
					<id>feff0694-99ab-11db-937f-000e0c431b59</id>
					<value>190</value>
				</price>
				<price>
					<id>288427e0-9732-11db-bbb4-0017315894a1</id>
					<value>199</value>
				</price>
			</prices>
			<propertiesValues>
				<propertyValue>
					<property>e8287600-ad96-11e3-b114-005056be1f7c</property>
					<value>DANOGIPS</value>
					<measure/>
				</propertyValue>
				<propertyValue>
					<property>cce0ab91-6a67-11e4-8945-005056be1f7a</property>
					<value>Россия</value>
					<measure/>
				</propertyValue>
				<propertyValue>
					<property>42d0b52f-970f-11e4-9be0-005056be1f7c</property>
					<value>пазогребневая гипсовая плита</value>
					<measure/>
				</propertyValue>
			</propertiesValues>
		</Item>
		<Item>
			<id>a6f80c96-516a-11dd-a89a-000e0c431b58</id>
			<itemName>Краска ВД акриловая д/обоев DALI 2,5л (Рогнеда)</itemName>
			<group>ab721020-ddae-11e4-8114-00155d3703b3</group>
			<amount>190</amount>
			<minAmount>37</minAmount>
			<description>Краска DALI акриловая для обоев обладает отличной адгезией к бумажным, флизелиновым и стеклообоям. Благодаря специально разработанному составу, краска DALI обладает хорошей укрывистостью и без проблем наносится на обои под покраску, сохраняя фактуру. Так же краска DALI может быть нанесена на минеральные поверхности, такие как гипсокартон, штукатурки, шпатлевки и тому подобные покрытия. Единственным условием к поверхности - нормальная влажность и температура в помещении, в котором производятся работы. Краска Dali содержит в составе специальные антибактериальные добавки, препятствующие образованию и размножению био организмов и бактерий. Кроме того краска DALI устойчива к влажной уборке и применению моющих средств, что делает стены и потолок помещения долговечными. Существуют две разновидности краски DALI - база А, подходящая и для машинной и для ручной колеровки, и база С, подходящая только для машинной колеровки. Купить и заколеровать краску DALI, а так же другую продукцию компании Рогнеда Вы можете в интернет магазине СтройБери, а так же в сети розничных магазинов.</description>
			<shown>1</shown>
			<action>0</action>
			<prices>
				<price>
					<id>86157e21-e56b-11dc-8b6b-000e0c431b58</id>
					<value>421,2</value>
				</price>
				<price>
					<id>feff0694-99ab-11db-937f-000e0c431b59</id>
					<value>486,68</value>
				</price>
				<price>
					<id>288427e0-9732-11db-bbb4-0017315894a1</id>
					<value>529</value>
				</price>
			</prices>
			<propertiesValues>
				<propertyValue>
					<property>d624040a-3bb6-11e3-80e1-005056be1f7a</property>
					<value>акриловая</value>
					<measure/>
				</propertyValue>
				<propertyValue>
					<property>0a552a3f-3bb7-11e3-80e1-005056be1f7a</property>
					<value>белый</value>
					<measure/>
				</propertyValue>
				<propertyValue>
					<property>27c97b3a-3bc1-11e3-80e1-005056be1f7a</property>
					<value>внутренние работы</value>
					<measure/>
				</propertyValue>
				<propertyValue>
					<property>e8287600-ad96-11e3-b114-005056be1f7c</property>
					<value>DALI</value>
					<measure/>
				</propertyValue>
				<propertyValue>
					<property>cce0ab91-6a67-11e4-8945-005056be1f7a</property>
					<value>Россия</value>
					<measure/>
				</propertyValue>
				<propertyValue>
					<property>6cd386f1-3a4b-11e3-88c8-005056be1f7a</property>
					<value/>
					<measure>л</measure>
				</propertyValue>
				<propertyValue>
					<property>bbea9c1a-3a4b-11e3-88c8-005056be1f7a</property>
					<value/>
					<measure/>
				</propertyValue>
				<propertyValue>
					<property>42d0b52f-970f-11e4-9be0-005056be1f7c</property>
					<value>краска</value>
					<measure/>
				</propertyValue>
			</propertiesValues>
		</Item>
	</Items>
</BodyUpload>